docs/source/conf.py
docs/source/queens.py
nucs/__init__.py
nucs/constants.py
nucs/heaps.py
nucs/numba_helper.py
nucs/examples/__init__.py
nucs/examples/default_argument_parser.py
nucs/examples/all_interval_series/__init__.py
nucs/examples/all_interval_series/__main__.py
nucs/examples/all_interval_series/all_interval_series_problem.py
nucs/examples/alpha/__init__.py
nucs/examples/alpha/__main__.py
nucs/examples/alpha/alpha_problem.py
nucs/examples/bibd/__init__.py
nucs/examples/bibd/__main__.py
nucs/examples/bibd/bibd_problem.py
nucs/examples/donald/__init__.py
nucs/examples/donald/__main__.py
nucs/examples/donald/donald_problem.py
nucs/examples/employee_scheduling/__init__.py
nucs/examples/employee_scheduling/__main__.py
nucs/examples/employee_scheduling/employee_scheduling_problem.py
nucs/examples/golomb/__init__.py
nucs/examples/golomb/__main__.py
nucs/examples/golomb/golomb_problem.py
nucs/examples/knapsack/__init__.py
nucs/examples/knapsack/__main__.py
nucs/examples/knapsack/knapsack_problem.py
nucs/examples/latin_square/__init__.py
nucs/examples/latin_square/__main__.py
nucs/examples/magic_sequence/__init__.py
nucs/examples/magic_sequence/__main__.py
nucs/examples/magic_sequence/magic_sequence_problem.py
nucs/examples/magic_square/__init__.py
nucs/examples/magic_square/__main__.py
nucs/examples/magic_square/magic_square_problem.py
nucs/examples/quasigroup/__init__.py
nucs/examples/quasigroup/__main__.py
nucs/examples/quasigroup/quasigroup_problem.py
nucs/examples/queens/__init__.py
nucs/examples/queens/__main__.py
nucs/examples/queens/queens_problem.py
nucs/examples/schur_lemma/__init__.py
nucs/examples/schur_lemma/__main__.py
nucs/examples/schur_lemma/schur_lemma_problem.py
nucs/examples/sports_tournament_scheduling/__init__.py
nucs/examples/sports_tournament_scheduling/__main__.py
nucs/examples/sports_tournament_scheduling/sports_tournament_scheduling_problem.py
nucs/examples/sudoku/__init__.py
nucs/examples/sudoku/sudoku_problem.py
nucs-9.0.0.dist-info/licenses/LICENSE.md
nucs-9.0.0.dist-info/METADATA
nucs-9.0.0.dist-info/WHEEL
nucs-9.0.0.dist-info/top_level.txt
nucs-9.0.0.dist-info/RECORD
