Metadata-Version: 2.4
Name: NuCS
Version: 9.0.0
Summary: A Numpy and Numba based Python library for solving Constraint Satisfaction Problems over finite domains
Author-email: Yan Georget <yan.georget@gmail.com>
Project-URL: Homepage, https://github.com/yangeorget/nucs
Project-URL: Issues, https://github.com/yangeorget/nucs/issues
Classifier: Development Status :: 5 - Production/Stable
Classifier: Intended Audience :: Developers
Classifier: Intended Audience :: Education
Classifier: Intended Audience :: Science/Research
Classifier: License :: OSI Approved :: MIT License
Classifier: Operating System :: OS Independent
Classifier: Programming Language :: Python :: 3
Classifier: Programming Language :: Python :: 3.11
Classifier: Programming Language :: Python :: 3.12
Classifier: Programming Language :: Python :: 3.13
Classifier: Topic :: Scientific/Engineering
Classifier: Topic :: Scientific/Engineering :: Artificial Intelligence
Classifier: Topic :: Scientific/Engineering :: Mathematics
Classifier: Topic :: Software Development :: Libraries
Classifier: Topic :: Software Development :: Libraries :: Python Modules
Requires-Python: >=3.11
License-File: LICENSE.md
Requires-Dist: numba==0.61.0
Requires-Dist: numpy==2.1.3
Requires-Dist: rich
Dynamic: license-file
